loglifos/__init__.py
loglifos/logs.py
loglifos-0.2.1.dist-info/LICENSE
loglifos-0.2.1.dist-info/METADATA
loglifos-0.2.1.dist-info/WHEEL
loglifos-0.2.1.dist-info/RECORD
